LICENSE
README.md
setup.py
gale/__init__.py
gale/mapper.py
gale_topo.egg-info/PKG-INFO
gale_topo.egg-info/SOURCES.txt
gale_topo.egg-info/dependency_links.txt
gale_topo.egg-info/requires.txt
gale_topo.egg-info/top_level.txt